ibutsu_utils/__init__.py
ibutsu_utils/download.py
ibutsu_utils/upload.py
ibutsu_utils/xmerge.py
ibutsu_utils-0.2.0.dist-info/METADATA
ibutsu_utils-0.2.0.dist-info/WHEEL
ibutsu_utils-0.2.0.dist-info/entry_points.txt
ibutsu_utils-0.2.0.dist-info/licenses/LICENSE
ibutsu_utils-0.2.0.dist-info/RECORD
