Metadata-Version: 2.1
Name: ibutsu-utils
Version: 0.2.0
Summary: Some command line utilities for Ibutsu
Project-URL: Bug Tracker, https://github.com/ibutsu/ibutsu-utils/issues
Project-URL: Homepage, https://ibutsu-project.org/
Project-URL: Source, https://github.com/ibutsu/ibutsu-utils
Author-email: Raoul Snyman <rsnyman@redhat.com>
License-File: LICENSE
Classifier: License :: OSI Approved :: MIT License
Classifier: Operating System :: OS Independent
Classifier: Programming Language :: Python :: 3
Requires-Python: >=3.6
Requires-Dist: ibutsu-client>=2.2.2
